CHANGES.txt
README.rst
README.txt
setup.cfg
setup.py
collective/__init__.py
collective.portlets.lineage.egg-info/PKG-INFO
collective.portlets.lineage.egg-info/SOURCES.txt
collective.portlets.lineage.egg-info/dependency_links.txt
collective.portlets.lineage.egg-info/entry_points.txt
collective.portlets.lineage.egg-info/namespace_packages.txt
collective.portlets.lineage.egg-info/not-zip-safe
collective.portlets.lineage.egg-info/requires.txt
collective.portlets.lineage.egg-info/top_level.txt
collective/portlets/__init__.py
collective/portlets/lineage/LineageEventsPortlet.py
collective/portlets/lineage/LineageNewsPortlet.py
collective/portlets/lineage/LineagePortletsCommon.py
collective/portlets/lineage/LineageRecentPortlet.py
collective/portlets/lineage/LineageReviewPortlet.py
collective/portlets/lineage/LineageSearchPortlet.py
collective/portlets/lineage/__init__.py
collective/portlets/lineage/configure.zcml
collective/portlets/lineage/version.txt
collective/portlets/lineage/Extensions/Install.py
collective/portlets/lineage/profiles/default/jsregistry.xml
collective/portlets/lineage/profiles/default/metadata.xml
collective/portlets/lineage/profiles/default/portlets.xml
collective/portlets/lineage/profiles/default/skins.xml
collective/portlets/lineage/profiles/uninstall/portlets.xml
collective/portlets/lineage/profiles/uninstall/skins.xml
collective/portlets/lineage/skins/scripts/livesearch.js
collective/portlets/lineage/skins/scripts/livesearch_reply.py
collective/portlets/lineage/skins/scripts/subsiteAdvancedQueryCatalog.py
collective/portlets/lineage/skins/scripts/subsiteRecentlyModified.py
collective/portlets/lineage/skins/templates/recently_modified.pt
collective/portlets/lineage/skins/templates/recently_modified.pt.metadata
collective/portlets/lineage/templates/events.pt
collective/portlets/lineage/templates/news.pt
collective/portlets/lineage/templates/recent.pt
collective/portlets/lineage/templates/review.pt
collective/portlets/lineage/templates/search.pt
collective/portlets/lineage/tests/__init__.py
collective/portlets/lineage/tests/base.py
collective/portlets/lineage/tests/test_portlet.py
docs/HISTORY.txt
docs/INSTALL.txt
docs/LICENSE.GPL
docs/LICENSE.txt