Metadata-Version: 1.0
Name: collective.portlets.lineage
Version: 1.2.9
Summary: A collection of collective.lineage aware portlets
Home-page: https://github.com/collective/collective.portlets.lineage
Author: Andy Leeb
Author-email: ableeb@andersonleeb.com
License: GPL
Keywords: plone portlets collective.lineage
Platform: UNKNOWN
Classifier: Framework :: Plone
Classifier: Programming Language :: Python
